pyramid_metrics/__init__.py
pyramid_metrics/tween.py
pyramid_metrics/utility.py
pyramid_metrics/tests/__init__.py
pyramid_metrics/tests/functional/__init__.py
pyramid_metrics/tests/functional/test.py
pyramid_metrics/tests/functional/test_failsafe.py
pyramid_metrics/tests/unittests/__init__.py
pyramid_metrics/tests/unittests/test_includeme.py
pyramid_metrics/tests/unittests/test_tween.py
pyramid_metrics/tests/unittests/test_utility.py
pyramid_metrics-0.3.1.dist-info/DESCRIPTION.rst
pyramid_metrics-0.3.1.dist-info/METADATA
pyramid_metrics-0.3.1.dist-info/RECORD
pyramid_metrics-0.3.1.dist-info/WHEEL
pyramid_metrics-0.3.1.dist-info/entry_points.txt
pyramid_metrics-0.3.1.dist-info/metadata.json
pyramid_metrics-0.3.1.dist-info/top_level.txt
