Metadata-Version: 2.0
Name: pyramid-metrics
Version: 0.3.1
Summary: Performance metrics for Pyramid using StatsD
Home-page: https://github.com/ludia/pyramid_metrics
Author: Pior Bastida
Author-email: pior@pbastida.net
License: BSD
Keywords: wsgi pylons pyramid statsd metric tween handler
Platform: UNKNOWN
Classifier: Development Status :: 4 - Beta
Classifier: Intended Audience :: Developers
Classifier: Programming Language :: Python
Classifier: Programming Language :: Python :: 2
Classifier: Programming Language :: Python :: 2.7
Classifier: Programming Language :: Python :: 3.3
Classifier: Programming Language :: Python :: 3.4
Classifier: Programming Language :: Python :: 3.5
Classifier: Programming Language :: Python :: 3.6
Classifier: Framework :: Pyramid
Classifier: Topic :: Internet :: WWW/HTTP :: WSGI
Requires-Dist: statsd (<2.2,>=2.1.2)
